{
  "世帯員": {
    "Alicia": {
      "誕生年月日": {
        "ETERNITY": "1980-01-01"
      },
      "所得": {
        "2017-01-01": 4000
      },
      "可処分所得": {
        "2017-01-01": null
      }
    },
    "Javier": {
      "誕生年月日": {
        "ETERNITY": "1984-01-01"
      },
      "所得": {
        "2017-01-01": 2500
      },
      "可処分所得": {
        "2017-01-01": null
      }
    }
  },
  "世帯": {
    "_": {
      "自分一覧": ["Alicia"],
      "配偶者一覧": ["Javier"],
      "福祉給付総額": {
        "2017-01-01": null
      },
      "税金総額": {
        "2017-01-01": null
      }
    }
  }
}
